MANIFEST.in
setup.py
django_secure_login.egg-info/PKG-INFO
django_secure_login.egg-info/SOURCES.txt
django_secure_login.egg-info/dependency_links.txt
django_secure_login.egg-info/not-zip-safe
django_secure_login.egg-info/requires.txt
django_secure_login.egg-info/top_level.txt
secure_login/__init__.py
secure_login/admin.py
secure_login/backends.py
secure_login/checkers.py
secure_login/forms.py
secure_login/models.py
secure_login/on_fail.py
secure_login/tests.py
secure_login/utils.py
secure_login/views.py