Metadata-Version: 1.1
Name: django-secure-login
Version: 0.3.4
Summary: Django app to harden the security around login
Home-page: http://github.com/agiliq/django-secure-login
Author: Agiliq
Author-email: hello@agiliq.com
License: BSD
Platform: UNKNOWN
Classifier: Development Status :: 3 - Alpha
Classifier: Environment :: Web Environment
Classifier: Intended Audience :: Developers
Classifier: License :: OSI Approved :: BSD License
Classifier: Operating System :: OS Independent
Classifier: Programming Language :: Python
Classifier: Framework :: Django
